quarter/__init__.py
quarter/quarter.py
quarter-0.0.4.dist-info/METADATA
quarter-0.0.4.dist-info/RECORD
quarter-0.0.4.dist-info/WHEEL
quarter-0.0.4.dist-info/top_level.txt
